ezyrb/__init__.py
ezyrb/database.py
ezyrb/parameter.py
ezyrb/reducedordermodel.py
ezyrb/regular_grid.py
ezyrb/snapshot.py
ezyrb/approximation/__init__.py
ezyrb/approximation/ann.py
ezyrb/approximation/approximation.py
ezyrb/approximation/gpr.py
ezyrb/approximation/kneighbors_regressor.py
ezyrb/approximation/linear.py
ezyrb/approximation/neighbors_regressor.py
ezyrb/approximation/radius_neighbors_regressor.py
ezyrb/approximation/rbf.py
ezyrb/parallel/__init__.py
ezyrb/parallel/ae.py
ezyrb/parallel/ae_eddl.py
ezyrb/parallel/ann.py
ezyrb/parallel/approximation.py
ezyrb/parallel/gpr.py
ezyrb/parallel/kneighbors_regressor.py
ezyrb/parallel/linear.py
ezyrb/parallel/neighbors_regressor.py
ezyrb/parallel/pod.py
ezyrb/parallel/radius_neighbors_regressor.py
ezyrb/parallel/rbf.py
ezyrb/parallel/reducedordermodel.py
ezyrb/parallel/reduction.py
ezyrb/plugin/__init__.py
ezyrb/plugin/aggregation.py
ezyrb/plugin/automatic_shift.py
ezyrb/plugin/database_splitter.py
ezyrb/plugin/plugin.py
ezyrb/plugin/scaler.py
ezyrb/plugin/shift.py
ezyrb/reduction/__init__.py
ezyrb/reduction/ae.py
ezyrb/reduction/pod.py
ezyrb/reduction/pod_ae.py
ezyrb/reduction/reduction.py
ezyrb-1.3.3.dist-info/licenses/LICENSE.rst
ezyrb-1.3.3.dist-info/METADATA
ezyrb-1.3.3.dist-info/WHEEL
ezyrb-1.3.3.dist-info/top_level.txt
ezyrb-1.3.3.dist-info/RECORD
