Metadata-Version: 2.4
Name: ezyrb
Version: 1.3.3
Summary: Easy Reduced Basis
Author-email: Nicola Demo <demo.nicola@gmail.com>, Marco Tezzele <marcotez@gmail.com>
License: MIT
Project-URL: Homepage, https://github.com/mathLab/EZyRB
Project-URL: Repository, https://github.com/mathLab/EZyRB
Project-URL: Documentation, http://mathlab.github.io/EZyRB/
Keywords: pod,interpolation,reduced-basis,model-order-reduction,scientific-computing
Requires-Python: >=3.8
License-File: LICENSE.rst
Requires-Dist: future
Requires-Dist: numpy
Requires-Dist: scipy
Requires-Dist: matplotlib
Requires-Dist: scikit-learn
Requires-Dist: torch
Requires-Dist: datasets
Provides-Extra: docs
Requires-Dist: sphinx; extra == "docs"
Requires-Dist: sphinx_rtd_theme; extra == "docs"
Provides-Extra: test
Requires-Dist: pytest; extra == "test"
Requires-Dist: pytest-cov; extra == "test"
Provides-Extra: dev
Requires-Dist: black; extra == "dev"
Requires-Dist: pylint; extra == "dev"
Dynamic: license-file
